{
  "$schema": "https://ui.shadcn.com/schema/registry-item.json",
  "name": "font-bricolage-grotesque",
  "type": "registry:file",
  "description": "Bricolage Grotesque font — served from DesignSync CDN. After install, add @import './font-bricolage-grotesque.css' to your globals.css.",
  "files": [
    {
      "path": "registry/styles/font-bricolage-grotesque.css",
      "type": "registry:file",
      "target": "app/font-bricolage-grotesque.css",
      "content": "@font-face {\n  font-family: 'Bricolage Grotesque';\n  font-style: normal;\n  font-weight: 400;\n  font-display: swap;\n  src: url('https://designsync-omega.vercel.app/fonts/Bricolage-Grotesque-400.woff2') format('woff2');\n  unicode-range: U+0000-00FF;\n}\n\n@font-face {\n  font-family: 'Bricolage Grotesque';\n  font-style: normal;\n  font-weight: 500;\n  font-display: swap;\n  src: url('https://designsync-omega.vercel.app/fonts/Bricolage-Grotesque-500.woff2') format('woff2');\n  unicode-range: U+0000-00FF;\n}\n\n@font-face {\n  font-family: 'Bricolage Grotesque';\n  font-style: normal;\n  font-weight: 700;\n  font-display: swap;\n  src: url('https://designsync-omega.vercel.app/fonts/Bricolage-Grotesque-700.woff2') format('woff2');\n  unicode-range: U+0000-00FF;\n}"
    }
  ]
}